Metadata-Version: 2.3
Name: just-semantic-search-server-cuda
Version: 2.5.0
Summary: Core interfaces for hybrid search implementations (CUDA version)
License: Apache-2.0
Keywords: python,llm,gpu,cuda,science,review,hybrid search,semantic search,agent
Author: Anton Kulaga
Author-email: antonkulaga@gmail.com
Requires-Python: >=3.10,<3.15
Classifier: Development Status :: 3 - Alpha
Classifier: Intended Audience :: Developers
Classifier: License :: OSI Approved :: Apache Software License
Classifier: Operating System :: MacOS :: MacOS X
Classifier: Operating System :: Microsoft :: Windows
Classifier: Operating System :: POSIX :: Linux
Classifier: Operating System :: Unix
Classifier: Programming Language :: Python :: 3
Classifier: Programming Language :: Python :: 3.10
Classifier: Programming Language :: Python :: 3.11
Classifier: Programming Language :: Python :: 3.12
Classifier: Programming Language :: Python :: 3.13
Classifier: Programming Language :: Python :: 3.14
Requires-Dist: just-agents-web (>=0.6.0)
Requires-Dist: just-semantic-search-meili-cuda
Requires-Dist: just-semantic-search-scholar-cuda
